README.md
setup.cfg
setup.py
kongclient/__init__.py
kongclient/client.py
kongclient/exceptions.py
kongclient/flask.py
kongclient/api/__init__.py
kongclient/api/base.py
kongclient/api/certificate.py
kongclient/api/consumer.py
kongclient/api/node_info.py
kongclient/api/plugin.py
kongclient/api/route.py
kongclient/api/service.py
kongclient/api/sni.py
kongclient/api/tag.py
kongclient/api/target.py
kongclient/api/upstream.py
python_kongclient.egg-info/PKG-INFO
python_kongclient.egg-info/SOURCES.txt
python_kongclient.egg-info/dependency_links.txt
python_kongclient.egg-info/requires.txt
python_kongclient.egg-info/top_level.txt