Metadata-Version: 2.1
Name: python-kongclient
Version: 1.1.1
Summary: A python library for the Kong admin API
Home-page: https://github.com/haintd/python-kongclient
Author: HaiNT
Author-email: tronghaibk2008@gmail.com
License: BSD
Platform: UNKNOWN
Classifier: Intended Audience :: Developers
Classifier: License :: OSI Approved :: BSD License
Classifier: Operating System :: OS Independent
Classifier: Programming Language :: Python :: 3
Classifier: Topic :: Internet :: WWW/HTTP :: Dynamic Content
Classifier: Topic :: Software Development :: Libraries :: Python Modules
Requires-Python: >=3.6
